<?xml version="1.1" encoding="UTF-8" standalone="no"?>
<databaseChangeLog xmlns="http://www.liquibase.org/xml/ns/dbchangelog" xmlns:ext="http://www.liquibase.org/xml/ns/dbchangelog-ext" xmlns:xsi="http://www.w3.org/2001/XMLSchema-instance" xsi:schemaLocation="http://www.liquibase.org/xml/ns/dbchangelog-ext http://www.liquibase.org/xml/ns/dbchangelog/dbchangelog-ext.xsd http://www.liquibase.org/xml/ns/dbchangelog http://www.liquibase.org/xml/ns/dbchangelog/dbchangelog-3.5.xsd">
    <changeSet author="mel (generated)" id="4eb10763-abc6-11ec-814d-1831bf981123-1">
        <createTable tableName="regions">
			<column name="Id" type="CHAR(36)">
                <constraints nullable="false" primaryKey="true"/>
            </column>
            <column name="Name" type="VARCHAR(256)">
                <constraints nullable="false"/>
            </column>
             <column name="Type" type="VARCHAR(50)">
                <constraints nullable="false"/>
            </column>
            <column name="ParentId" type="Char(36)" />
            <column name="IsEnabled" type="BIT" />			
        </createTable>
    </changeSet>
</databaseChangeLog>
